[{"name": "pitodb", "mode": 1, "owner": null, "tables": [{"name": "tbcalificacion", "inherits": null, "columns": [{"name": "idcalifica", "type": "INTEGER", "size": null, "PK": true, "FK": null, "NN": true, "Default": null, "Unique": null, "Constraint": null}, {"name": "item", "type": "VARCHAR", "size": 100, "PK": false, "FK": null, "NN": true, "Default": null, "Unique": null, "Constraint": null}, {"name": "punteo", "type": "INTEGER", "size": null, "PK": false, "FK": null, "NN": true, "Default": null, "Unique": null, "Constraint": null}]}, {"name": "tbproducto", "inherits": null, "columns": [{"name": "idproducto", "type": "INTEGER", "size": null, "PK": true, "FK": null, "NN": true, "Default": null, "Unique": null, "Constraint": null}, {"name": "producto", "type": "VARCHAR", "size": 150, "PK": false, "FK": null, "NN": true, "Default": null, "Unique": null, "Constraint": null}, {"name": "fechacreacion", "type": "DATE", "size": null, "PK": false, "FK": null, "NN": true, "Default": null, "Unique": null, "Constraint": null}, {"name": "estado", "type": "INTEGER", "size": null, "PK": false, "FK": null, "NN": false, "Default": null, "Unique": null, "Constraint": null}]}]}, {"name": "curiosex", "mode": 1, "owner": null, "tables": []}, {"name": "jkgjkd", "mode": 1, "owner": null, "tables": []}]